crandas/main.py
crandas-0.1.dist-info/METADATA
crandas-0.1.dist-info/WHEEL
crandas-0.1.dist-info/entry_points.txt
crandas-0.1.dist-info/top_level.txt
crandas-0.1.dist-info/RECORD
